{
	"info": {
		"_postman_id": "7c014f8c-b250-4085-8459-f124648e2f3c",
		"name": "Canton TX Fetcher API",
		"description": "API collection for Canton Network validator wallet operations based on CantonTxFetcher",
		"schema": "https://schema.getpostman.com/json/collection/v2.0.0/collection.json",
		"_exporter_id": "24307033"
	},
	"item": [
		{
			"name": "Authentication",
			"item": [
				{
					"name": "Get Auth0 Token",
					"event": [
						{
							"listen": "test",
							"script": {
								"exec": [
									"var jsonData = pm.response.json();",
									"if (jsonData.access_token) {",
									"    pm.collectionVariables.set('accessToken', jsonData.access_token);",
									"    console.log('Access token saved successfully');",
									"}"
								],
								"type": "text/javascript",
								"packages": {},
								"requests": {}
							}
						}
					],
					"request": {
						"method": "POST",
						"header": [
							{
								"key": "Content-Type",
								"value": "application/json"
							}
						],
						"body": {
							"mode": "raw",
							"raw": "{\n  \"grant_type\": \"http://auth0.com/oauth/grant-type/password-realm\",\n  \"realm\": \"{{dbRealm}}\",\n  \"username\": \"{{username}}\",\n  \"password\": \"{{password}}\",\n  \"client_id\": \"{{clientId}}\",\n  \"client_secret\": \"{{clientSecret}}\",\n  \"audience\": \"{{audienceTemplate}}\",\n  \"scope\": \"openid profile email\"\n}"
						},
						"url": "{{auth0Domain}}",
						"description": "Fetches an Auth0 access token for authenticating with Canton API endpoints. The token is automatically saved to the collection variable 'accessToken'."
					},
					"response": []
				}
			],
			"description": "Authentication endpoints for obtaining access tokens"
		},
		{
			"name": "Wallet Operations",
			"item": [
				{
					"name": "Get Transactions",
					"request": {
						"method": "POST",
						"header": [
							{
								"key": "Content-Type",
								"value": "application/json"
							},
							{
								"key": "Authorization",
								"value": "Bearer {{accessToken}}"
							}
						],
						"body": {
							"mode": "raw",
							"raw": "{\n  \"page_size\": 1000,\n  \"begin_after_id\": null\n}"
						},
						"url": "{{baseUrl}}/validator/v0/wallet/transactions",
						"description": "Fetches a paginated list of wallet transactions. Use 'begin_after_id' with an event_id from the last transaction to paginate through results."
					},
					"response": []
				},
				{
					"name": "Get Transactions (with pagination)",
					"request": {
						"method": "POST",
						"header": [
							{
								"key": "Content-Type",
								"value": "application/json"
							},
							{
								"key": "Authorization",
								"value": "Bearer {{accessToken}}"
							}
						],
						"body": {
							"mode": "raw",
							"raw": "{\n  \"page_size\": 100,\n  \"begin_after_id\": \"#1220fa1c4f3c1e11ab8521eb118e727607fb5581a3723276e5ebb1270dd536c4594b:1\"\n}"
						},
						"url": "{{baseUrl}}/validator/v0/wallet/transactions",
						"description": "Fetches a paginated list of wallet transactions starting after a specific event_id. Replace '<event_id_from_last_transaction>' with an actual event_id."
					},
					"response": []
				},
				{
					"name": "Get Balance",
					"request": {
						"method": "GET",
						"header": [
							{
								"key": "Content-Type",
								"value": "application/json"
							},
							{
								"key": "Authorization",
								"value": "Bearer {{accessToken}}"
							}
						],
						"url": "{{baseUrl}}/validator/v0/wallet/balance",
						"description": "Fetches the current wallet balance for the validator."
					},
					"response": []
				},
				{
					"name": "Get User Status",
					"request": {
						"method": "GET",
						"header": [
							{
								"key": "Content-Type",
								"value": "application/json"
							},
							{
								"key": "Authorization",
								"value": "Bearer {{accessToken}}"
							}
						],
						"url": "{{baseUrl}}/validator/v0/wallet/user-status",
						"description": "Fetches the current user status including party_id for the validator."
					},
					"response": []
				}
			],
			"description": "Core wallet operations including transactions, balance, and user status"
		},
		{
			"name": "Reward Coupons",
			"item": [
				{
					"name": "Get Validator Reward Coupons",
					"request": {
						"method": "GET",
						"header": [
							{
								"key": "Content-Type",
								"value": "application/json"
							},
							{
								"key": "Authorization",
								"value": "Bearer {{accessToken}}"
							}
						],
						"url": "{{baseUrl}}/validator/v0/wallet/validator-reward-coupons",
						"description": "Fetches the list of validator reward coupons (contracts)."
					},
					"response": []
				},
				{
					"name": "Get App Reward Coupons",
					"request": {
						"method": "GET",
						"header": [
							{
								"key": "Content-Type",
								"value": "application/json"
							},
							{
								"key": "Authorization",
								"value": "Bearer {{accessToken}}"
							}
						],
						"url": "{{baseUrl}}/validator/v0/wallet/app-reward-coupons",
						"description": "Fetches the list of app reward coupons."
					},
					"response": []
				},
				{
					"name": "Get Validator Faucet Coupons",
					"request": {
						"method": "GET",
						"header": [
							{
								"key": "Content-Type",
								"value": "application/json"
							},
							{
								"key": "Authorization",
								"value": "Bearer {{accessToken}}"
							}
						],
						"url": "{{baseUrl}}/validator/v0/wallet/validator-faucet-coupons",
						"description": "Fetches the list of validator faucet coupons."
					},
					"response": []
				}
			],
			"description": "Endpoints for fetching various reward coupons"
		},
		{
			"name": "Transfers & Payments",
			"item": [
				{
					"name": "Get Accepted App Payments",
					"request": {
						"method": "GET",
						"header": [
							{
								"key": "Content-Type",
								"value": "application/json"
							},
							{
								"key": "Authorization",
								"value": "Bearer {{accessToken}}"
							}
						],
						"url": "{{baseUrl}}/validator/v0/wallet/accepted-app-payments",
						"description": "Fetches the list of accepted app payments."
					},
					"response": []
				},
				{
					"name": "Get Accepted Transfer Offers",
					"request": {
						"method": "GET",
						"header": [
							{
								"key": "Content-Type",
								"value": "application/json"
							},
							{
								"key": "Authorization",
								"value": "Bearer {{accessToken}}"
							}
						],
						"url": "{{baseUrl}}/validator/v0/wallet/accepted-transfer-offers",
						"description": "Fetches the list of accepted transfer offers."
					},
					"response": []
				}
			],
			"description": "Endpoints for transfers and payment operations"
		}
	],
	"event": [
		{
			"listen": "prerequest",
			"script": {
				"type": "text/javascript",
				"exec": [
					"// Pre-request script to check if token exists",
					"// If you want auto-refresh, you can add token validation logic here"
				]
			}
		},
		{
			"listen": "test",
			"script": {
				"type": "text/javascript",
				"exec": [
					"// Global test script",
					"pm.test('Status code is 200', function () {",
					"    pm.response.to.have.status(200);",
					"});"
				]
			}
		}
	],
	"variable": [
		{
			"key": "validatorName",
			"value": "arkhia",
			"type": "string"
		},
		{
			"key": "baseUrl",
			"value": "http://canton.api.nodeops.ninja/{{validatorName}}/api",
			"type": "string"
		},
		{
			"key": "auth0Domain",
			"value": "https://bcw-canton-mainnet.us.auth0.com/oauth/token",
			"type": "string"
		},
		{
			"key": "clientId",
			"value": "abcd123",
			"type": "string"
		},
		{
			"key": "clientSecret",
			"value": "somesecretvalue",
			"type": "string"
		},
		{
			"key": "audienceTemplate",
			"value": "https://{{validatorName}}-canton-mainnet.nodeops.ninja",
			"type": "string"
		},
		{
			"key": "username",
			"value": "data@bcw.group",
			"type": "string"
		},
		{
			"key": "password",
			"value": "mypassword",
			"type": "string"
		},
		{
			"key": "dbRealm",
			"value": "Username-Password-Authentication",
			"type": "string"
		},
		{
			"key": "accessToken",
			"value": "",
			"type": "string"
		}
	]
}