{"record_time":"2026-03-19T15:00:00Z","migration_id":4,"computed_as_of_round":88096,"summaries":[{"party_id":"Blockscape-validator-1::12206e0c85df8d9172aa7bc5c943f60b5367c2a24bae12a7b480a6b659c70ec474c7","total_unlocked_coin":"15258.6206846757","total_locked_coin":"5932.7665277973","total_coin_holdings":"21191.3872124730","accumulated_holding_fees_unlocked":"0.0030166524","accumulated_holding_fees_locked":"16.3643505897","accumulated_holding_fees_total":"16.3673672421","total_available_coin":"15258.6176680233"}]}